spqr_quant/__init__.py
spqr_quant/inference.py
spqr_quant/sparse_util.py
spqr_quant/inference_kernels/__init__.py
spqr_quant/inference_kernels/common.cuh
spqr_quant/inference_kernels/cuda_kernel.py
spqr_quant/inference_kernels/kernel_selector.py
spqr_quant/inference_kernels/spqr_cuda.cpp
spqr_quant/inference_kernels/spqr_cuda_kernel.cu
spqr_quant-0.2.0.dist-info/METADATA
spqr_quant-0.2.0.dist-info/WHEEL
spqr_quant-0.2.0.dist-info/top_level.txt
spqr_quant-0.2.0.dist-info/RECORD
